cli/main.py
engine/main.py
templates/fastapi_starter/.env
templates/fastapi_starter/.env.example
templates/fastapi_starter/.gitignore
templates/fastapi_starter/Dockerfile
templates/fastapi_starter/README.md
templates/fastapi_starter/app/__init__.py
templates/fastapi_starter/app/__main__.py
templates/fastapi_starter/app/api/__init__.py
templates/fastapi_starter/app/api/deps.py
templates/fastapi_starter/app/api/endpoints/__init__.py
templates/fastapi_starter/app/api/endpoints/auth.py
templates/fastapi_starter/app/api/endpoints/users.py
templates/fastapi_starter/app/core/__init__.py
templates/fastapi_starter/app/core/database.py
templates/fastapi_starter/app/core/security.py
templates/fastapi_starter/app/core/settings.py
templates/fastapi_starter/app/main.py
templates/fastapi_starter/app/models/__init__.py
templates/fastapi_starter/app/models/user.py
templates/fastapi_starter/app/schemas/__init__.py
templates/fastapi_starter/app/schemas/user.py
templates/fastapi_starter/docker-compose.yml
templates/fastapi_starter/melia.yml
templates/fastapi_starter/pyproject.toml
templates/fastapi_starter/tests/__init__.py
templates/fastapi_starter/tests/test_main.py
templates/fastapi_starter/tree.json
melia_fastapi-0.5.0.dist-info/METADATA
melia_fastapi-0.5.0.dist-info/WHEEL
melia_fastapi-0.5.0.dist-info/entry_points.txt
melia_fastapi-0.5.0.dist-info/RECORD
