Metadata-Version: 2.3
Name: melia-fastapi
Version: 0.5.0
Summary: fastapi project generator and servicemanager
Author: el hadji
Author-email: elhadji.sarr@outlook.com
Requires-Python: >=3.11,<4.0
Classifier: Programming Language :: Python :: 3
Classifier: Programming Language :: Python :: 3.11
Classifier: Programming Language :: Python :: 3.12
Classifier: Programming Language :: Python :: 3.13
Requires-Dist: click (>=8.2.1,<9.0.0)
Requires-Dist: jinja2 (>=3.1.6,<4.0.0)
